sbsky/bin/bsky.py
sbsky/lib/bsky.py
sbsky/lib/mistune_plugins.py
sbsky/lib/text_builder.py
sbsky-0.1.1.dist-info/METADATA
sbsky-0.1.1.dist-info/WHEEL
sbsky-0.1.1.dist-info/entry_points.txt
sbsky-0.1.1.dist-info/RECORD
