Metadata-Version: 2.1
Name: sbsky
Version: 0.1.1
Summary: Bluesky Terminal Client
Author: Sanhaji Omar
Author-email: sanhaji.omar@gmail.com
Requires-Python: >=3.8,<3.13
Classifier: Programming Language :: Python :: 3
Classifier: Programming Language :: Python :: 3.8
Classifier: Programming Language :: Python :: 3.9
Classifier: Programming Language :: Python :: 3.10
Classifier: Programming Language :: Python :: 3.11
Classifier: Programming Language :: Python :: 3.12
Requires-Dist: atproto (>=0.0.43,<0.0.44)
Requires-Dist: fire (>=0.5.0,<0.6.0)
Requires-Dist: loguru (>=0.7.2,<0.8.0)
Requires-Dist: mistune (>=3.0.2,<4.0.0)
